TcpipXieyiRumenjiaochengCYuyanBianchengWangFix1/README.md
TcpipXieyiRumenjiaochengCYuyanBianchengWangFix1/__init__.py
TcpipXieyiRumenjiaochengCYuyanBianchengWangFix1/__main__.py
TcpipXieyiRumenjiaochengCYuyanBianchengWangFix1/file.epub
TcpipXieyiRumenjiaochengCYuyanBianchengWangFix1/index.html
TcpipXieyiRumenjiaochengCYuyanBianchengWangFix1/css/__init__.py
TcpipXieyiRumenjiaochengCYuyanBianchengWangFix1/css/annotations.css
TcpipXieyiRumenjiaochengCYuyanBianchengWangFix1/css/main.css
TcpipXieyiRumenjiaochengCYuyanBianchengWangFix1/css/normalize.css
TcpipXieyiRumenjiaochengCYuyanBianchengWangFix1/css/popup.css
TcpipXieyiRumenjiaochengCYuyanBianchengWangFix1/font/__init__.py
TcpipXieyiRumenjiaochengCYuyanBianchengWangFix1/font/fontello.eot
TcpipXieyiRumenjiaochengCYuyanBianchengWangFix1/font/fontello.svg
TcpipXieyiRumenjiaochengCYuyanBianchengWangFix1/font/fontello.ttf
TcpipXieyiRumenjiaochengCYuyanBianchengWangFix1/font/fontello.woff
TcpipXieyiRumenjiaochengCYuyanBianchengWangFix1/img/__init__.py
TcpipXieyiRumenjiaochengCYuyanBianchengWangFix1/img/annotator-glyph-sprite.png
TcpipXieyiRumenjiaochengCYuyanBianchengWangFix1/img/annotator-icon-sprite.png
TcpipXieyiRumenjiaochengCYuyanBianchengWangFix1/img/apple-touch-icon.png
TcpipXieyiRumenjiaochengCYuyanBianchengWangFix1/img/cancelfullscreen.png
TcpipXieyiRumenjiaochengCYuyanBianchengWangFix1/img/close.png
TcpipXieyiRumenjiaochengCYuyanBianchengWangFix1/img/fullscreen.png
TcpipXieyiRumenjiaochengCYuyanBianchengWangFix1/img/loader.gif
TcpipXieyiRumenjiaochengCYuyanBianchengWangFix1/img/menu-icon.png
TcpipXieyiRumenjiaochengCYuyanBianchengWangFix1/img/save.png
TcpipXieyiRumenjiaochengCYuyanBianchengWangFix1/img/saved.png
TcpipXieyiRumenjiaochengCYuyanBianchengWangFix1/img/settings-s.png
TcpipXieyiRumenjiaochengCYuyanBianchengWangFix1/img/settings.png
TcpipXieyiRumenjiaochengCYuyanBianchengWangFix1/img/star.png
TcpipXieyiRumenjiaochengCYuyanBianchengWangFix1/js/__init__.py
tcpip_xieyi_rumenjiaocheng_c_yuyan_biancheng_wang_fix1-2025.3.24.1.dist-info/METADATA
tcpip_xieyi_rumenjiaocheng_c_yuyan_biancheng_wang_fix1-2025.3.24.1.dist-info/WHEEL
tcpip_xieyi_rumenjiaocheng_c_yuyan_biancheng_wang_fix1-2025.3.24.1.dist-info/entry_points.txt
tcpip_xieyi_rumenjiaocheng_c_yuyan_biancheng_wang_fix1-2025.3.24.1.dist-info/top_level.txt
tcpip_xieyi_rumenjiaocheng_c_yuyan_biancheng_wang_fix1-2025.3.24.1.dist-info/RECORD
